gh_whatsapp-0.1.0.dist-info/licenses/LICENSE
gupshup/__init__.py
gupshup/client.py
gupshup/send.py
gupshup/send_template.py
gh_whatsapp-0.1.0.dist-info/METADATA
gh_whatsapp-0.1.0.dist-info/WHEEL
gh_whatsapp-0.1.0.dist-info/top_level.txt
gh_whatsapp-0.1.0.dist-info/RECORD
