Metadata-Version: 2.4
Name: gh-whatsapp
Version: 0.1.0
Summary: Python SDK para integração com a API de WhatsApp da Gupshup
Home-page: https://github.com/casarolifabio/gupshup-whatsapp
Author: Casaroli Fabio
Author-email: fabiocasarolij@gmail.com
Classifier: Programming Language :: Python :: 3
Classifier: Operating System :: OS Independent
Classifier: License :: OSI Approved :: MIT License
Classifier: Development Status :: 3 - Alpha
Classifier: Intended Audience :: Developers
Classifier: Topic :: Communications :: Chat
Requires-Python: >=3.7
License-File: LICENSE
Dynamic: author
Dynamic: author-email
Dynamic: classifier
Dynamic: description
Dynamic: description-content-type
Dynamic: home-page
Dynamic: license-file
Dynamic: requires-python
Dynamic: summary
